symeo_python/__init__.py
symeo_python/config.py
symeo_python/api_client/__init__.py
symeo_python/api_client/symeo_api_client.py
symeo_python/cli/__init__.py
symeo_python/cli/cli.py
symeo_python/cli/main.py
symeo_python/cli/process_runner.py
symeo_python/cli/symeo_python_cli.py
symeo_python/configuration/__init__.py
symeo_python/configuration/config_loader.py
symeo_python/configuration/config_parser.py
symeo_python/configuration/config_validator.py
symeo_python/configuration/configuration.py
symeo_python/yaml_converter/__init__.py
symeo_python/yaml_converter/yaml_to_class_converter.py
symeo_python-0.0.5.dist-info/METADATA
symeo_python-0.0.5.dist-info/WHEEL
symeo_python-0.0.5.dist-info/entry_points.txt
symeo_python-0.0.5.dist-info/top_level.txt
symeo_python-0.0.5.dist-info/RECORD
